CHANGES.txt
COPYRIGHT.txt
LICENSE.txt
README.txt
setup.cfg
setup.py
docs/Makefile
docs/conf.py
docs/index.rst
docs/.static/logo_hi.gif
docs/.static/repoze.css
repoze/__init__.py
repoze.browserid.egg-info/PKG-INFO
repoze.browserid.egg-info/SOURCES.txt
repoze.browserid.egg-info/dependency_links.txt
repoze.browserid.egg-info/entry_points.txt
repoze.browserid.egg-info/namespace_packages.txt
repoze.browserid.egg-info/not-zip-safe
repoze.browserid.egg-info/requires.txt
repoze.browserid.egg-info/top_level.txt
repoze/browserid/__init__.py
repoze/browserid/middleware.py
repoze/browserid/tests.py